motile_tracker/__init__.py
motile_tracker/__main__.py
motile_tracker/_version.py
motile_tracker/example_data.py
motile_tracker/launcher.py
motile_tracker/napari.yaml
motile_tracker/application_menus/__init__.py
motile_tracker/application_menus/editing_menu.py
motile_tracker/application_menus/main_app.py
motile_tracker/application_menus/menu_widget.py
motile_tracker/application_menus/visualization_widget.py
motile_tracker/data_views/__init__.py
motile_tracker/data_views/graph_attributes.py
motile_tracker/data_views/_tests/conftest.py
motile_tracker/data_views/_tests/test_center_view.py
motile_tracker/data_views/_tests/test_force_operations.py
motile_tracker/data_views/_tests/test_link_clipping_planes.py
motile_tracker/data_views/_tests/test_ortho_views.py
motile_tracker/data_views/_tests/test_track_labels.py
motile_tracker/data_views/_tests/test_tree_widget_utils.py
motile_tracker/data_views/_tests/test_visualization_widget.py
motile_tracker/data_views/views/__init__.py
motile_tracker/data_views/views/ortho_views.py
motile_tracker/data_views/views/layers/__init__.py
motile_tracker/data_views/views/layers/click_utils.py
motile_tracker/data_views/views/layers/contour_labels.py
motile_tracker/data_views/views/layers/track_graph.py
motile_tracker/data_views/views/layers/track_labels.py
motile_tracker/data_views/views/layers/track_points.py
motile_tracker/data_views/views/layers/tracks_layer_group.py
motile_tracker/data_views/views/tree_view/__init__.py
motile_tracker/data_views/views/tree_view/flip_axes_widget.py
motile_tracker/data_views/views/tree_view/navigation_widget.py
motile_tracker/data_views/views/tree_view/tree_view_feature_widget.py
motile_tracker/data_views/views/tree_view/tree_view_mode_widget.py
motile_tracker/data_views/views/tree_view/tree_widget.py
motile_tracker/data_views/views/tree_view/tree_widget_utils.py
motile_tracker/data_views/views_coordinator/__init__.py
motile_tracker/data_views/views_coordinator/groups.py
motile_tracker-4.3.0.dist-info/licenses/LICENSE
motile_tracker-4.3.0.dist-info/METADATA
motile_tracker-4.3.0.dist-info/WHEEL
motile_tracker-4.3.0.dist-info/entry_points.txt
motile_tracker-4.3.0.dist-info/top_level.txt
motile_tracker-4.3.0.dist-info/RECORD
