Metadata-Version: 2.4
Name: motile-tracker
Version: 4.3.0
Summary: Application for interactive tracking with global optimization
Author-email: Caroline Malin-Mayor <malinmayorc@janelia.hhmi.org>
License: BSD 3-Clause License
Project-URL: Bug Tracker, https://github.com/funkelab/motile_tracker/issues
Project-URL: Documentation, https://funkelab.github.io/motile_tracker/
Classifier: Development Status :: 5 - Production/Stable
Classifier: Framework :: napari
Classifier: Intended Audience :: Developers
Classifier: Intended Audience :: End Users/Desktop
Classifier: Intended Audience :: Science/Research
Classifier: License :: OSI Approved :: BSD License
Classifier: Operating System :: OS Independent
Classifier: Programming Language :: Python
Classifier: Programming Language :: Python :: 3
Classifier: Programming Language :: Python :: 3 :: Only
Classifier: Programming Language :: Python :: 3.11
Classifier: Programming Language :: Python :: 3.12
Classifier: Programming Language :: Python :: 3.13
Classifier: Topic :: Scientific/Engineering :: Image Processing
Requires-Python: >=3.11
License-File: LICENSE
Requires-Dist: napari<1,>=0.6.2
Requires-Dist: funtracks<2,>=1.7.0-a2
Requires-Dist: appdirs<2,>=1
Requires-Dist: numpy<3,>=2
Requires-Dist: magicgui>=0.10.1
Requires-Dist: qtpy<3,>=2.4
Requires-Dist: scikit-image>=0.25
Requires-Dist: motile>=0.3
Requires-Dist: motile_toolbox==0.4.0
Requires-Dist: pydantic<3,>=2
Requires-Dist: tifffile[all]>=2025.1.10
Requires-Dist: tqdm<5,>=4
Requires-Dist: dask[array]>=2021.10.0
Requires-Dist: fonticon-fontawesome6<7,>=6
Requires-Dist: pyqtgraph<1,>=0.13
Requires-Dist: napari-orthogonal-views>=0.0.9
Requires-Dist: lxml_html_clean<1,>=0.4
Requires-Dist: zarr<4,>=2.18.7
Provides-Extra: numba
Requires-Dist: numba>=0.62.1; extra == "numba"
Provides-Extra: gurobi
Requires-Dist: gurobipy; extra == "gurobi"
Provides-Extra: gurobi12
Requires-Dist: gurobipy<13,>=12; extra == "gurobi12"
Provides-Extra: gurobi13
Requires-Dist: gurobipy<14,>=13; extra == "gurobi13"
Provides-Extra: all
Requires-Dist: pyqt6<7,>=6.7; extra == "all"
Dynamic: license-file
